sandtank_xai/__init__.py
sandtank_xai/app/__init__.py
sandtank_xai/app/jupyter.py
sandtank_xai/app/main.py
sandtank_xai/app/ui.py
sandtank_xai/app/engine/__init__.py
sandtank_xai/app/engine/refs/Init_press.pfb
sandtank_xai/app/engine/refs/perm.pfb
sandtank_xai/app/engine/xai/__init__.py
sandtank_xai/app/engine/xai/colors.py
sandtank_xai/app/engine/xai/ml.py
sandtank_xai/html/__init__.py
sandtank_xai/html/module/__init__.py
sandtank_xai/html/module/serve/demo.html
sandtank_xai/html/module/serve/vue-sandtank_xai.common.js
sandtank_xai/html/module/serve/vue-sandtank_xai.common.js.map
sandtank_xai/html/module/serve/vue-sandtank_xai.umd.js
sandtank_xai/html/module/serve/vue-sandtank_xai.umd.js.map
sandtank_xai/html/module/serve/vue-sandtank_xai.umd.min.js
sandtank_xai/html/module/serve/vue-sandtank_xai.umd.min.js.map
trame_sandtank_xai-2.0.0.dist-info/LICENSE
trame_sandtank_xai-2.0.0.dist-info/METADATA
trame_sandtank_xai-2.0.0.dist-info/WHEEL
trame_sandtank_xai-2.0.0.dist-info/entry_points.txt
trame_sandtank_xai-2.0.0.dist-info/top_level.txt
trame_sandtank_xai-2.0.0.dist-info/RECORD
